surfadev/__init__.py
surfadev/client.py
surfadev/completeness.py
surfadev/config.py
surfadev/default_config.py
surfadev/session.py
surfadev/utils.py
surfadev-0.2.2.dist-info/METADATA
surfadev-0.2.2.dist-info/WHEEL
surfadev-0.2.2.dist-info/RECORD
