Metadata-Version: 2.4
Name: surfadev
Version: 0.2.2
Summary: Analytics SDK for tracking user events and sending them to Supabase. Built for MCP (Model Context Protocol) servers.
Project-URL: Homepage, https://github.com/surfadev/surfadev
Project-URL: Documentation, https://github.com/surfadev/surfadev#readme
Project-URL: Repository, https://github.com/surfadev/surfadev
Project-URL: Issues, https://github.com/surfadev/surfadev/issues
Author-email: Surfadev <support@surfadev.com>
License: MIT
Keywords: analytics,event-tracking,mcp,metrics,model-context-protocol,sdk,supabase,telemetry
Classifier: Development Status :: 4 - Beta
Classifier: Intended Audience :: Developers
Classifier: License :: OSI Approved :: MIT License
Classifier: Programming Language :: Python :: 3
Classifier: Programming Language :: Python :: 3.11
Classifier: Programming Language :: Python :: 3.12
Classifier: Programming Language :: Python :: 3.13
Classifier: Topic :: Internet :: WWW/HTTP :: Dynamic Content
Classifier: Topic :: Software Development :: Libraries :: Python Modules
Classifier: Topic :: System :: Monitoring
Requires-Python: >=3.11
Requires-Dist: openai>=1.0.0
Requires-Dist: python-dotenv>=1.0.0
Requires-Dist: supabase>=2.0.0
Provides-Extra: dev
Requires-Dist: black>=23.0.0; extra == 'dev'
Requires-Dist: pytest-asyncio>=0.23.0; extra == 'dev'
Requires-Dist: pytest>=8.0.0; extra == 'dev'
Requires-Dist: ruff>=0.1.0; extra == 'dev'
